Metadata-Version: 2.1
Name: django-fsa
Version: 2.7.1
Summary: Django friendly finite state machine support, forked from django-fsm
Home-page: http://github.com/mdziwny/django-fsm
Author: Antoine Fontaine
Author-email: antoine.fontaine@gmail.com
License: MIT License
Keywords: django
Platform: any
Classifier: Development Status :: 5 - Production/Stable
Classifier: Environment :: Web Environment
Classifier: Intended Audience :: Developers
Classifier: License :: OSI Approved :: MIT License
Classifier: Operating System :: OS Independent
Classifier: Framework :: Django
Classifier: Framework :: Django :: 1.11
Classifier: Programming Language :: Python
Classifier: Programming Language :: Python :: 2.7
Classifier: Programming Language :: Python :: 3
Classifier: Programming Language :: Python :: 3.4
Classifier: Programming Language :: Python :: 3.5
Classifier: Programming Language :: Python :: 3.6
Classifier: Programming Language :: Python :: 3.7
Classifier: Framework :: Django
Classifier: Topic :: Software Development :: Libraries :: Python Modules
